leanbase/__init__.py
leanbase/api.py
leanbase/constants.py
leanbase/evaluate.py
leanbase/exceptions.py
leanbase/client/__init__.py
leanbase/client/lbconvey.py
leanbase/client/sse.py
leanbase/models/__init__.py
leanbase/models/condition.py
leanbase/models/config.py
leanbase/models/feature.py
leanbase/models/segment.py
leanbase/models/user.py
leanbase/storage/__init__.py
leanbase/storage/inmemory.py
leanbase/tasks/__init__.py
leanbase/tasks/workers.py
tests/__init__.py
tests/fixtures.py
tests/start-client.py
tests/test_decode.py
tests/test_evaluate.py
leanbase-1.6.0.dist-info/LICENSE
leanbase-1.6.0.dist-info/METADATA
leanbase-1.6.0.dist-info/WHEEL
leanbase-1.6.0.dist-info/top_level.txt
leanbase-1.6.0.dist-info/RECORD
