Metadata-Version: 2.1
Name: leanbase
Version: 1.6.0
Summary: A client for the leanbase API.
Home-page: https://github.com/leanbase/leanbase-python
Author: Dipanjan Mukherjee
Author-email: dipanjan@leanbase.io
License: UNKNOWN
Platform: UNKNOWN
Classifier: Programming Language :: Python :: 3
Classifier: License :: OSI Approved :: MIT License
Classifier: Operating System :: OS Independent
Requires-Dist: six (==1.12.0)
Requires-Dist: sseclient (==0.0.24)
Provides-Extra: test
Requires-Dist: nose (==1.3.7) ; extra == 'test'
Requires-Dist: twine (==1.13.0) ; extra == 'test'
Requires-Dist: bumpversion (==0.5.3) ; extra == 'test'
